memory_plus/__init__.py
memory_plus/mcp.py
memory_plus/memory_protocol.py
memory_plus/utils.py
memory_plus-0.1.6.dist-info/METADATA
memory_plus-0.1.6.dist-info/WHEEL
memory_plus-0.1.6.dist-info/entry_points.txt
memory_plus-0.1.6.dist-info/licenses/LICENSE
memory_plus-0.1.6.dist-info/RECORD
